example/__init__.py
example/admin.py
example/models.py
nested_inline/__init__.py
nested_inline/admin.py
nested_inline/static/admin/css/forms-nested.css
nested_inline/static/admin/js/inlines-nested.js
nested_inline/static/admin/js/inlines-nested.min.js
nested_inline/templates/admin/edit_inline/stacked-nested.html
nested_inline/templates/admin/edit_inline/tabular-nested.html
django_nested_inline_springboard-0.3.8.dist-info/LICENSE
django_nested_inline_springboard-0.3.8.dist-info/METADATA
django_nested_inline_springboard-0.3.8.dist-info/WHEEL
django_nested_inline_springboard-0.3.8.dist-info/top_level.txt
django_nested_inline_springboard-0.3.8.dist-info/RECORD
