Metadata-Version: 2.1
Name: django-nested-inline-springboard
Version: 0.3.8
Summary: Recursive nesting of inline forms for Django Admin
Home-page: https://github.com/sliderule-labs/django-nested-inline-springboard
Author: Josh Rowe
Author-email: josh@s-block.com
License: MIT License
Platform: UNKNOWN
Classifier: Development Status :: 4 - Beta
Classifier: Environment :: Web Environment
Classifier: Framework :: Django
Classifier: Intended Audience :: Developers
Classifier: License :: OSI Approved :: MIT License
Classifier: Operating System :: OS Independent
Classifier: Programming Language :: Python
Classifier: Programming Language :: Python :: 3
Classifier: Topic :: Software Development :: Libraries :: Python Modules
